deepmage-0.2.1.data/scripts/deepmage
deepmage-0.2.1.data/scripts/deepmage-hexdump
deepmage-0.2.1.data/scripts/deepmage-hexparse
deepmage-0.2.1.dist-info/LICENSE.txt
deepmage-0.2.1.dist-info/METADATA
deepmage-0.2.1.dist-info/RECORD
deepmage-0.2.1.dist-info/WHEEL
deepmage-0.2.1.dist-info/top_level.txt
libdeepmage/__init__.py
libdeepmage/bitstream_reader.hy
libdeepmage/cursor.hy
libdeepmage/deepmage.py
libdeepmage/parser.hy
