Metadata-Version: 2.1
Name: deepmage
Version: 0.2.1
Summary: Hex editor for bit-level occultism
Home-page: https://github.com/mmiszczyk/deepmage
Author: Maciej Miszczyk
Author-email: maciejmmiszczyk@gmail.com
License: GPL 3
Platform: UNKNOWN
Classifier: Programming Language :: Python :: 3
Classifier: Programming Language :: Lisp
Classifier: Operating System :: OS Independent
Classifier: Environment :: Console
Classifier: Intended Audience :: Developers
Classifier: Intended Audience :: Information Technology
Classifier: Intended Audience :: System Administrators
Classifier: Intended Audience :: Telecommunications Industry
Classifier: Topic :: Security
Classifier: Topic :: Software Development :: Embedded Systems
Requires-Python: >=3
Requires-Dist: hy
Requires-Dist: bitstring
Requires-Dist: asciimatics
